google_trends.py
google_trends-1.1.dist-info/LICENSE
google_trends-1.1.dist-info/METADATA
google_trends-1.1.dist-info/WHEEL
google_trends-1.1.dist-info/top_level.txt
google_trends-1.1.dist-info/RECORD
